udsi/__init__.py
udsi/client.py
udsi/models.py
udsi/utils.py
udsi-0.1.1.dist-info/LICENSE
udsi-0.1.1.dist-info/WHEEL
udsi-0.1.1.dist-info/METADATA
udsi-0.1.1.dist-info/RECORD
