Metadata-Version: 2.1
Name: udsi
Version: 0.1.1
Summary: Unlimited Drive Storage Improved
Author: elliott-maguire
Author-email: me@elliott-m.com
Requires-Python: >=3.7,<4.0
Classifier: Programming Language :: Python :: 3
Classifier: Programming Language :: Python :: 3.7
Requires-Dist: google-api-python-client (>=1.7,<2.0)
Requires-Dist: google-auth (>=1.6,<2.0)
Requires-Dist: requests (>=2.20,<3.0)
